latex_utils/__init__.py
latex_utils/latex_utils.py
latex_utils_TheRaphael0000-0.0.3.dist-info/LICENSE
latex_utils_TheRaphael0000-0.0.3.dist-info/METADATA
latex_utils_TheRaphael0000-0.0.3.dist-info/WHEEL
latex_utils_TheRaphael0000-0.0.3.dist-info/top_level.txt
latex_utils_TheRaphael0000-0.0.3.dist-info/RECORD
